pia/__init__.py
pia/__main__.py
pia/_version.py
pia/proc.py
pia/py.typed
pia-0.2.0.dist-info/LICENSE
pia-0.2.0.dist-info/METADATA
pia-0.2.0.dist-info/WHEEL
pia-0.2.0.dist-info/entry_points.txt
pia-0.2.0.dist-info/top_level.txt
pia-0.2.0.dist-info/RECORD
